grpc_load_balancer/__init__.py
grpc_load_balancer/connection_counter.py
grpc_load_balancer/env_config_loader.py
grpc_load_balancer/grpc_connection_forwarder.py
grpc_load_balancer/lock_with_value.py
grpc_load_balancer/metrics_based_server_finder.py
grpc_load_balancer-0.0.3.dist-info/LICENSE
grpc_load_balancer-0.0.3.dist-info/METADATA
grpc_load_balancer-0.0.3.dist-info/WHEEL
grpc_load_balancer-0.0.3.dist-info/top_level.txt
grpc_load_balancer-0.0.3.dist-info/RECORD
