Metadata-Version: 2.1
Name: grpc-load-balancer
Version: 0.0.3
Summary: A small toolset to implement load balancing for gRPC services
Home-page: https://github.com/flagman/grpc-load-balancer
Author: Pavel Malay
Author-email: flagmansupport@gmail.com
Classifier: Programming Language :: Python :: 3
Classifier: License :: OSI Approved :: MIT License
Classifier: Operating System :: OS Independent
License-File: LICENSE
Requires-Dist: requests
